PrediProt-1.0.16.data/scripts/PrediProt
PrediProt-1.0.16.data/scripts/PrediProt_GUI
PrediProt-1.0.16.data/scripts/PrediProt_getfasta
prediprot/PrediProt
prediprot/PrediProt_GUI
prediprot/PrediProt_getfasta
prediprot/__init__.py
prediprot/imports/__init__.py
prediprot/imports/prediprot_classes.py
prediprot/imports/prediprot_functions.py
prediprot/imports/prediprot_optimize.py
PrediProt-1.0.16.dist-info/LICENSE
PrediProt-1.0.16.dist-info/METADATA
PrediProt-1.0.16.dist-info/WHEEL
PrediProt-1.0.16.dist-info/top_level.txt
PrediProt-1.0.16.dist-info/RECORD
