Metadata-Version: 2.1
Name: PrediProt
Version: 1.0.16
Summary: Protein complex structure predictor
Home-page: https://pypi.org/project/PrediProt/
Author: The Dream Team
License: MIT
Platform: UNKNOWN
Requires-Python: >=3.6
Requires-Dist: argparse
